dashai_plugin_image_classification/__init__.py
dashai_plugin_image_classification/dataloader_class_template.py
dashai_plugin_image_classification/metric_class_template.py
dashai_plugin_image_classification/model_class_template.py
dashai_plugin_image_classification/task_class_template.py
dashai_plugin_image_classification-1.1.dist-info/METADATA
dashai_plugin_image_classification-1.1.dist-info/WHEEL
dashai_plugin_image_classification-1.1.dist-info/entry_points.txt
dashai_plugin_image_classification-1.1.dist-info/RECORD
